README.md
setup.cfg
setup.py
kaf/__init__.py
kaf/app.py
kaf.egg-info/PKG-INFO
kaf.egg-info/SOURCES.txt
kaf.egg-info/dependency_links.txt
kaf.egg-info/requires.txt
kaf.egg-info/top_level.txt
test/test_app.py