Metadata-Version: 2.1
Name: kaf
Version: 0.1.10
Summary: A mini-framework for Kafka apps
Home-page: https://github.com/skipperkongen/kaf
Author: Pimin Konstantin Kefaloukos
Author-email: skipperkongen@gmail.com
License: MIT
Download-URL: https://github.com/skipperkongen/kaf/archive/v0.1.10.tar.gz
Platform: UNKNOWN
Classifier: Programming Language :: Python :: 3
Classifier: License :: OSI Approved :: MIT License
Classifier: Operating System :: OS Independent
